odoo/addons/product_categ_image/README.rst
odoo/addons/product_categ_image/__init__.py
odoo/addons/product_categ_image/__manifest__.py
odoo/addons/product_categ_image/i18n/es.po
odoo/addons/product_categ_image/i18n/it.po
odoo/addons/product_categ_image/i18n/product_categ_image.pot
odoo/addons/product_categ_image/models/__init__.py
odoo/addons/product_categ_image/models/product_category.py
odoo/addons/product_categ_image/static/description/icon.png
odoo/addons/product_categ_image/views/product_view.xml
odoo14_addon_product_categ_image-14.0.1.0.1.dev6.dist-info/METADATA
odoo14_addon_product_categ_image-14.0.1.0.1.dev6.dist-info/WHEEL
odoo14_addon_product_categ_image-14.0.1.0.1.dev6.dist-info/top_level.txt
odoo14_addon_product_categ_image-14.0.1.0.1.dev6.dist-info/RECORD
